{
    "id": 16,
    "name": "鞋靴箱包",
    "children": [
        {
            "id": 20006,
            "name": "女鞋",
            "children": [
                {
                    "id": 20225,
                    "name": "低帮鞋",
                    "children": [
                        {
                            "id": 22450,
                            "name": "布鞋"
                        },
                        {
                            "id": 22449,
                            "name": "单鞋"
                        },
                        {
                            "id": 36986,
                            "name": "汉服鞋"
                        },
                        {
                            "id": 22459,
                            "name": "乐福鞋/豆豆鞋"
                        },
                        {
                            "id": 36985,
                            "name": "棉鞋"
                        },
                        {
                            "id": 22455,
                            "name": "穆勒鞋"
                        },
                        {
                            "id": 22454,
                            "name": "牛津鞋"
                        },
                        {
                            "id": 22462,
                            "name": "时尚休闲鞋"
                        },
                        {
                            "id": 22453,
                            "name": "松糕/摇摇鞋"
                        },
                        {
                            "id": 22460,
                            "name": "休闲板鞋"
                        }
                    ]
                },
                {
                    "id": 20226,
                    "name": "帆布鞋"
                },
                {
                    "id": 20227,
                    "name": "高帮鞋"
                },
                {
                    "id": 20228,
                    "name": "高跟鞋",
                    "children": [
                        {
                            "id": 22463,
                            "name": "方根高跟鞋"
                        },
                        {
                            "id": 36974,
                            "name": "婚鞋"
                        },
                        {
                            "id": 22456,
                            "name": "坡跟鞋"
                        },
                        {
                            "id": 22464,
                            "name": "细跟高跟鞋"
                        }
                    ]
                },
                {
                    "id": 20184,
                    "name": "凉鞋",
                    "children": [
                        {
                            "id": 22373,
                            "name": "洞洞鞋"
                        },
                        {
                            "id": 34718,
                            "name": "罗马凉鞋"
                        },
                        {
                            "id": 22420,
                            "name": "时尚休闲沙滩鞋"
                        },
                        {
                            "id": 22405,
                            "name": "时装凉鞋"
                        },
                        {
                            "id": 34717,
                            "name": "一字带凉鞋"
                        }
                    ]
                },
                {
                    "id": 20249,
                    "name": "女鞋配件"
                },
                {
                    "id": 20185,
                    "name": "拖鞋",
                    "children": [
                        {
                            "id": 22376,
                            "name": "包头拖"
                        },
                        {
                            "id": 34716,
                            "name": "棉拖"
                        },
                        {
                            "id": 22375,
                            "name": "人字拖"
                        },
                        {
                            "id": 22374,
                            "name": "一字拖"
                        }
                    ]
                },
                {
                    "id": 20187,
                    "name": "靴子",
                    "children": [
                        {
                            "id": 22400,
                            "name": "弹力靴/袜靴"
                        },
                        {
                            "id": 22335,
                            "name": "短靴"
                        },
                        {
                            "id": 22378,
                            "name": "马丁靴"
                        },
                        {
                            "id": 36987,
                            "name": "棉靴"
                        },
                        {
                            "id": 22406,
                            "name": "切尔西靴"
                        },
                        {
                            "id": 22416,
                            "name": "时尚雪地靴"
                        },
                        {
                            "id": 22377,
                            "name": "时装靴"
                        }
                    ]
                },
                {
                    "id": 20186,
                    "name": "雨鞋"
                }
            ]
        },
        {
            "id": 20010,
            "name": "男鞋",
            "children": [
                {
                    "id": 20235,
                    "name": "低帮鞋",
                    "children": [
                        {
                            "id": 22452,
                            "name": "布鞋"
                        },
                        {
                            "id": 22451,
                            "name": "单鞋"
                        },
                        {
                            "id": 22465,
                            "name": "时尚休闲鞋"
                        },
                        {
                            "id": 22457,
                            "name": "网面鞋"
                        },
                        {
                            "id": 22461,
                            "name": "休闲板鞋"
                        },
                        {
                            "id": 36778,
                            "name": "正装皮鞋"
                        }
                    ]
                },
                {
                    "id": 20236,
                    "name": "帆布鞋"
                },
                {
                    "id": 20237,
                    "name": "高帮鞋",
                    "children": [
                        {
                            "id": 36981,
                            "name": "高帮棉鞋"
                        },
                        {
                            "id": 36982,
                            "name": "高帮皮鞋"
                        },
                        {
                            "id": 36983,
                            "name": "高帮休闲鞋"
                        },
                        {
                            "id": 22458,
                            "name": "工装鞋"
                        }
                    ]
                },
                {
                    "id": 20202,
                    "name": "凉鞋",
                    "children": [
                        {
                            "id": 22387,
                            "name": "洞洞鞋"
                        },
                        {
                            "id": 22386,
                            "name": "沙滩鞋"
                        }
                    ]
                },
                {
                    "id": 20255,
                    "name": "男鞋配件"
                },
                {
                    "id": 20204,
                    "name": "皮鞋",
                    "children": [
                        {
                            "id": 22404,
                            "name": "乐福鞋/豆豆鞋"
                        },
                        {
                            "id": 22391,
                            "name": "牛津鞋"
                        },
                        {
                            "id": 22413,
                            "name": "休闲皮鞋"
                        }
                    ]
                },
                {
                    "id": 20203,
                    "name": "拖鞋",
                    "children": [
                        {
                            "id": 22390,
                            "name": "包头拖"
                        },
                        {
                            "id": 34719,
                            "name": "棉拖"
                        },
                        {
                            "id": 22389,
                            "name": "人字拖"
                        },
                        {
                            "id": 22388,
                            "name": "一字拖"
                        }
                    ]
                },
                {
                    "id": 20206,
                    "name": "靴子",
                    "children": [
                        {
                            "id": 22393,
                            "name": "马丁靴"
                        },
                        {
                            "id": 36984,
                            "name": "棉靴"
                        },
                        {
                            "id": 22414,
                            "name": "切尔西靴"
                        },
                        {
                            "id": 22417,
                            "name": "时尚雪地靴"
                        },
                        {
                            "id": 22392,
                            "name": "时装靴"
                        }
                    ]
                },
                {
                    "id": 20205,
                    "name": "雨鞋"
                }
            ]
        },
        {
            "id": 20011,
            "name": "箱包",
            "children": [
                {
                    "id": 20256,
                    "name": "功能箱包",
                    "children": [
                        {
                            "id": 22500,
                            "name": "登山包"
                        },
                        {
                            "id": 22499,
                            "name": "电脑包"
                        },
                        {
                            "id": 22495,
                            "name": "拉杆包"
                        },
                        {
                            "id": 22496,
                            "name": "旅行包"
                        },
                        {
                            "id": 22512,
                            "name": "旅行配件"
                        },
                        {
                            "id": 22497,
                            "name": "旅行箱"
                        },
                        {
                            "id": 36783,
                            "name": "手提箱"
                        },
                        {
                            "id": 22483,
                            "name": "书包"
                        },
                        {
                            "id": 22519,
                            "name": "休闲运动包"
                        },
                        {
                            "id": 22485,
                            "name": "腰包/胸包"
                        },
                        {
                            "id": 22518,
                            "name": "专业相机包"
                        }
                    ]
                },
                {
                    "id": 20207,
                    "name": "卡套"
                },
                {
                    "id": 20258,
                    "name": "男士包袋",
                    "children": [
                        {
                            "id": 22487,
                            "name": "单肩/斜挎包"
                        },
                        {
                            "id": 22489,
                            "name": "卡包/名片夹/钥匙包"
                        },
                        {
                            "id": 22514,
                            "name": "男士钱包"
                        },
                        {
                            "id": 22513,
                            "name": "男士手包"
                        },
                        {
                            "id": 22521,
                            "name": "男士双肩包"
                        },
                        {
                            "id": 22522,
                            "name": "男士钥匙包"
                        },
                        {
                            "id": 22520,
                            "name": "商务公文包"
                        },
                        {
                            "id": 22509,
                            "name": "手机包"
                        },
                        {
                            "id": 22510,
                            "name": "证件包"
                        }
                    ]
                },
                {
                    "id": 20257,
                    "name": "女士包袋",
                    "children": [
                        {
                            "id": 22502,
                            "name": "单肩包"
                        },
                        {
                            "id": 22501,
                            "name": "化妆包"
                        },
                        {
                            "id": 22488,
                            "name": "卡包/证件包/零钱包"
                        },
                        {
                            "id": 22484,
                            "name": "钱包"
                        },
                        {
                            "id": 22506,
                            "name": "手机包"
                        },
                        {
                            "id": 22504,
                            "name": "手拿包"
                        },
                        {
                            "id": 22505,
                            "name": "手提包"
                        },
                        {
                            "id": 22503,
                            "name": "双肩包"
                        },
                        {
                            "id": 22507,
                            "name": "斜挎包"
                        },
                        {
                            "id": 22508,
                            "name": "钥匙包"
                        },
                        {
                            "id": 36975,
                            "name": "腋下包"
                        }
                    ]
                },
                {
                    "id": 20267,
                    "name": "箱包相关配件"
                }
            ]
        }
    ]
}